deep_tts/__init__.py
deep_tts/common.py
deep_tts/data_models.py
deep_tts-0.1.19.dist-info/METADATA
deep_tts-0.1.19.dist-info/WHEEL
deep_tts-0.1.19.dist-info/RECORD
