Metadata-Version: 2.1
Name: deep-tts
Version: 0.1.19
Summary: 
Author: xfeng
Author-email: it.support@deepgrain.ai
Requires-Python: >=3.10,<4.0
Classifier: Programming Language :: Python :: 3
Classifier: Programming Language :: Python :: 3.10
Classifier: Programming Language :: Python :: 3.11
Classifier: Programming Language :: Python :: 3.12
Requires-Dist: fastapi (>=0.110.0,<0.111.0)
Requires-Dist: pyjwt (>=2.8.0,<3.0.0)
Requires-Dist: python-dotenv (>=1.0.1,<2.0.0)
Requires-Dist: python-multipart (>=0.0.9,<0.0.10)
Requires-Dist: requests (>=2.31.0,<3.0.0)
Requires-Dist: uvicorn[standard] (>=0.29.0,<0.30.0)
Requires-Dist: watchdog (>=4.0.0,<5.0.0)
